aws_environ_loader/__init__.py
aws_environ_loader/aws_secret_manager.py
aws_environ_loader/env_resolver.py
aws_environ_loader-1.0.2.dist-info/LICENSE
aws_environ_loader-1.0.2.dist-info/METADATA
aws_environ_loader-1.0.2.dist-info/WHEEL
aws_environ_loader-1.0.2.dist-info/top_level.txt
aws_environ_loader-1.0.2.dist-info/RECORD
